{
	"name": "Southridge_ADLS_Gen2",
	"properties": {
		"linkedServiceName": {
			"referenceName": "Southridge_ADLS_Gen2",
			"type": "LinkedServiceReference"
		},
		"parameters": {
			"directory": {
				"type": "string"
			},
			"file": {
				"type": "string"
			}
		},
		"annotations": [],
		"type": "Json",
		"typeProperties": {
			"location": {
				"type": "AzureBlobFSLocation",
				"fileName": {
					"value": "@dataset().file",
					"type": "Expression"
				},
				"folderPath": {
					"value": "@dataset().directory",
					"type": "Expression"
				}
			}
		},
		"schema": {}
	}
}